LICENSE.txt
README.md
setup.py
example/Computer.py
example/__init__.py
example/__main__.py
moxom/__init__.py
moxom/helper.py
moxom/moxom.py
moxom/runtime.py
moxom/runtime_context.py
moxom/types.py
moxom.egg-info/PKG-INFO
moxom.egg-info/SOURCES.txt
moxom.egg-info/dependency_links.txt
moxom.egg-info/top_level.txt
moxom/compiler/__init__.py
moxom/compiler/astparser.py
moxom/compiler/cstparser.py
moxom/compiler/interpreter.py
moxom/compiler/lexer.py
moxom/compiler/operators.py