Metadata-Version: 2.1
Name: moxom
Version: 1.0.0
Summary: Library to build simple user-friendly CLI API for your Python scripts
Home-page: https://github.com/sikrinick/moxom
Author: Mykyta Sikriier
Author-email: sikrinick@gmail.com
License: UNKNOWN
Platform: UNKNOWN
Classifier: Programming Language :: Python :: 3
Classifier: License :: OSI Approved :: MIT License
Classifier: Operating System :: OS Independent
Requires-Python: >=3.6
